mm_toolbox/__init__.py
mm_toolbox/candles/__init__.py
mm_toolbox/candles/base.pxd
mm_toolbox/candles/base.pyi
mm_toolbox/candles/base.pyx
mm_toolbox/candles/multi.pxd
mm_toolbox/candles/multi.pyi
mm_toolbox/candles/multi.pyx
mm_toolbox/candles/price.pxd
mm_toolbox/candles/price.pyi
mm_toolbox/candles/price.pyx
mm_toolbox/candles/tick.pxd
mm_toolbox/candles/tick.pyi
mm_toolbox/candles/tick.pyx
mm_toolbox/candles/time.pxd
mm_toolbox/candles/time.pyi
mm_toolbox/candles/time.pyx
mm_toolbox/candles/volume.pxd
mm_toolbox/candles/volume.pyi
mm_toolbox/candles/volume.pyx
mm_toolbox/logging/__init__.py
mm_toolbox/logging/advanced/README.md
mm_toolbox/logging/advanced/__init__.py
mm_toolbox/logging/advanced/config.pxd
mm_toolbox/logging/advanced/config.pyi
mm_toolbox/logging/advanced/config.pyx
mm_toolbox/logging/advanced/handlers/__init__.py
mm_toolbox/logging/advanced/handlers/base.py
mm_toolbox/logging/advanced/handlers/discord.py
mm_toolbox/logging/advanced/handlers/file.py
mm_toolbox/logging/advanced/handlers/telegram.py
mm_toolbox/logging/advanced/log.pxd
mm_toolbox/logging/advanced/master.pxd
mm_toolbox/logging/advanced/master.pyi
mm_toolbox/logging/advanced/master.pyx
mm_toolbox/logging/advanced/protocol.pxd
mm_toolbox/logging/advanced/protocol.pyx
mm_toolbox/logging/advanced/pylog.py
mm_toolbox/logging/advanced/pylog.pyi
mm_toolbox/logging/advanced/worker.pxd
mm_toolbox/logging/advanced/worker.pyi
mm_toolbox/logging/advanced/worker.pyx
mm_toolbox/logging/standard/__init__.py
mm_toolbox/logging/standard/config.py
mm_toolbox/logging/standard/handlers/__init__.py
mm_toolbox/logging/standard/handlers/base.py
mm_toolbox/logging/standard/handlers/discord.py
mm_toolbox/logging/standard/handlers/file.py
mm_toolbox/logging/standard/handlers/telegram.py
mm_toolbox/logging/standard/logger.py
mm_toolbox/misc/filter/__init__.py
mm_toolbox/misc/filter/core.pxd
mm_toolbox/misc/filter/core.pyi
mm_toolbox/misc/filter/core.pyx
mm_toolbox/misc/limiter/__init__.py
mm_toolbox-1.0.0.dist-info/WHEEL
mm_toolbox-1.0.0.dist-info/METADATA
mm_toolbox-1.0.0.dist-info/RECORD
