Metadata-Version: 2.4
Name: mm-toolbox
Version: 1.0.0
Summary: High-performance Python tools for market making systems
Keywords: market making,hft,high-frequency trading,trading,cython,performance
Author: beatzxbt
Author-email: beatzxbt <121855680+beatzxbt@users.noreply.github.com>
License-Expression: MIT
Classifier: Development Status :: 5 - Production/Stable
Classifier: Intended Audience :: Developers
Classifier: Intended Audience :: Financial and Insurance Industry
Classifier: Natural Language :: English
Classifier: Operating System :: OS Independent
Classifier: Programming Language :: Python :: 3
Classifier: Programming Language :: Python :: 3 :: Only
Classifier: Programming Language :: Python :: 3.12
Classifier: Programming Language :: Python :: 3.13
Classifier: Programming Language :: Python :: Implementation :: CPython
Classifier: Topic :: Office/Business :: Financial :: Investment
Classifier: Topic :: Software Development :: Libraries :: Python Modules
Classifier: Topic :: Scientific/Engineering
Classifier: Typing :: Typed
Requires-Dist: numpy
Requires-Dist: picows
Requires-Dist: ciso8601
Requires-Dist: msgspec
Requires-Dist: zmq
Requires-Dist: aiohttp
Requires-Python: >=3.12, <3.14
Project-URL: homepage, https://github.com/beatzxbt/mm-toolbox
Project-URL: repository, https://github.com/beatzxbt/mm-toolbox
